gsbfs/.DS_Store
gsbfs/__about__.py
gsbfs/__init__.py
gsbfs/gsbfs.py
gsbfs-0.0.1.dist-info/METADATA
gsbfs-0.0.1.dist-info/WHEEL
gsbfs-0.0.1.dist-info/entry_points.txt
gsbfs-0.0.1.dist-info/license_files/LICENSE
gsbfs-0.0.1.dist-info/RECORD
