Metadata-Version: 2.1
Name: gsbfs
Version: 0.0.1
Summary: Gram-Schmidt Boruta Feature Selection.
Project-URL: Issues, https://github.com/tomcv/gsbfs/issues
Project-URL: Source, https://github.com/tomcv/gsbfs
Author-email: Thomas Civeit <thomas@civeit.com>
License: MIT License
Keywords: feature-engineering,feature-extraction,feature-selection,machine-learning
Classifier: License :: OSI Approved :: MIT License
Classifier: Operating System :: OS Independent
Classifier: Programming Language :: Python :: 3.10
Classifier: Programming Language :: Python :: 3.11
Classifier: Programming Language :: Python :: 3.9
Requires-Python: >=3.9
Requires-Dist: numpy
Requires-Dist: scipy
